{
  "Temperature": "Temperature",
  "Atmosphere": "Atmosphere",
  "TemperatureHint": "0 = Earth (-20..+20°C), geology adds heat",
  "AtmosphereHint": "0 = Earth atmosphere, geology adds outgassing",
  "Geologic": "Geologic",
  "Noise Freq": "Noise Freq",
  "Seed": "Seed",
  "Octaves": "Octaves",
  "Density": "Density",
  "Radius": "Radius",
  "Displace": "Displace",
  "Segments": "Segments",
  "StarCount": "Stars",
  "MutationSpeed": "Mutation Speed",
  "AutoMutationInterval": "Auto Mutation (sec)",
  "MutationFields": "Mutation Fields",
  "Regenerate": "Regenerate",
  "Mutate": "Mutate",
  "Planet": "Planet",
  "Creature": "Creature",
  "Menu": "Menu",
  "Console": "Console",
  "Clear": "Clear",
  "Volume": "Volume",
  "Audio": "Audio",
  "AudioUnavailable": "(Audio device not available)",
  "Exit": "Exit",
  "Language": "Language",
  "Russian": "Russian",
  "English": "English",
  "ShowPawns": "Show pawns",
  "Pawns3D": "3D pawns",
  "Pawns": "Pawns",
  "SpeciesDNA": "Species DNA",
  "RandomizeDNA": "Randomize DNA",
  "MutateDNA": "Mutate DNA",
  "ApplyDNA": "Apply DNA (respawn population)",
  "CreatureAppearance": "Appearance",
  "Title": "SpaceDNA | T:{0:F2} A:{1:F2} G:{2:F2} F:{3:F2}",
  "SlidersShown": "Sliders shown",
  "SlidersHidden": "Sliders hidden",
  "TraitsHeader": "Traits ( [+] ok, [~] edge, [X] impossible ):",
  "Id": "Id",
  "Gen": "Gen",
  "Energy": "Energy",
  "Legs": "Legs",
  "Water": "Water",
  "Size": "Size"
}